veri_agents_api/__init__.py
veri_agents_api/fastapi/__init__.py
veri_agents_api/fastapi/thread/__init__.py
veri_agents_api/fastapi/thread/conftest.py
veri_agents_api/fastapi/thread/heal.py
veri_agents_api/fastapi/thread/live_test_api.py
veri_agents_api/fastapi/thread/router.py
veri_agents_api/fastapi/thread/schema.py
veri_agents_api/fastapi/thread/test_api.py
veri_agents_api/fastapi/thread/__snapshots__/test_api.ambr
veri_agents_api/threads_util/__init__.py
veri_agents_api/threads_util/checkpointer.py
veri_agents_api/threads_util/schema.py
veri_agents_api/util/__init__.py
veri_agents_api/util/awaitable.py
veri_agents_api-0.1.8.dist-info/METADATA
veri_agents_api-0.1.8.dist-info/WHEEL
veri_agents_api-0.1.8.dist-info/RECORD
