Metadata-Version: 2.4
Name: veri-agents-api
Version: 0.1.8
Summary: Veritone Agents Toolkit: API
Author-email: Markus Toman <mtoman@veritone.com>, Teo Boley <tboley@veritone.com>
Requires-Python: >=3.12
Requires-Dist: veri-agents-common[langgraph]>=0.1.1
Provides-Extra: dev
Requires-Dist: langchain-aws>=0.2.21; extra == 'dev'
Requires-Dist: uvicorn>=0.34.2; extra == 'dev'
Requires-Dist: veri-agents-common[fastapi,langfuse]>=0.1.1; extra == 'dev'
Provides-Extra: fastapi
Requires-Dist: veri-agents-common[fastapi,langfuse]>=0.1.1; extra == 'fastapi'
Provides-Extra: fastapi-dev
Requires-Dist: langchain-aws>=0.2.21; extra == 'fastapi-dev'
Requires-Dist: uvicorn>=0.34.2; extra == 'fastapi-dev'
Requires-Dist: veri-agents-common[fastapi,langfuse]>=0.1.1; extra == 'fastapi-dev'
